[{"nama":"SMK IT MIFTAHUL HUDA","sekolah_id":"4E873380-966D-417F-8ADF-79A417AB75BC","npsn":69872009,"jumlah_kirim":251,"ptk":3,"pegawai":2,"pd":135,"rombel":4,"jml_rk":5,"jml_lab":1,"jml_perpus":1,"induk_kecamatan":"Kec. Bungbulang","kode_wilayah_induk_kecamatan":"021103  ","induk_kabupaten":"Kab. Garut","kode_wilayah_induk_kabupaten":"021100  ","induk_provinsi":"Prov. Jawa Barat","kode_wilayah_induk_provinsi":"020000  ","bentuk_pendidikan":"SMK","status_sekolah":"Swasta","sinkron_terakhir":"02 Oct 2020 04:28:05","sekolah_id_enkrip":"2A7A500246C8C6685927                                                                                "},{"nama":"SMKS BINA BAKTI BUNGBULANG","sekolah_id":"99A40031-5C56-463B-97B7-64C3C80A0B44","npsn":69759027,"jumlah_kirim":8,"ptk":4,"pegawai":1,"pd":41,"rombel":3,"jml_rk":3,"jml_lab":1,"jml_perpus":0,"induk_kecamatan":"Kec. Bungbulang","kode_wilayah_induk_kecamatan":"021103  ","induk_kabupaten":"Kab. Garut","kode_wilayah_induk_kabupaten":"021100  ","induk_provinsi":"Prov. Jawa Barat","kode_wilayah_induk_provinsi":"020000  ","bentuk_pendidikan":"SMK","status_sekolah":"Swasta","sinkron_terakhir":"25 Sep 2020 22:56:00","sekolah_id_enkrip":"1E771323CC6910810F77                                                                                "},{"nama":"SMKS NURUL UYUN BUNGBULANG","sekolah_id":"3F8232CB-94A4-4849-ADC3-1D1C473C6EA9","npsn":69833578,"jumlah_kirim":15,"ptk":5,"pegawai":3,"pd":166,"rombel":5,"jml_rk":4,"jml_lab":0,"jml_perpus":0,"induk_kecamatan":"Kec. Bungbulang","kode_wilayah_induk_kecamatan":"021103  ","induk_kabupaten":"Kab. Garut","kode_wilayah_induk_kabupaten":"021100  ","induk_provinsi":"Prov. Jawa Barat","kode_wilayah_induk_provinsi":"020000  ","bentuk_pendidikan":"SMK","status_sekolah":"Swasta","sinkron_terakhir":"15 Sep 2020 20:59:06","sekolah_id_enkrip":"234DAB49EB7015129BF2                                                                                "},{"nama":"SMKS PGRI BUNGBULANG","sekolah_id":"A6BDB125-5F2C-4401-A734-A4947B478877","npsn":20227483,"jumlah_kirim":44,"ptk":20,"pegawai":6,"pd":656,"rombel":20,"jml_rk":20,"jml_lab":1,"jml_perpus":1,"induk_kecamatan":"Kec. Bungbulang","kode_wilayah_induk_kecamatan":"021103  ","induk_kabupaten":"Kab. Garut","kode_wilayah_induk_kabupaten":"021100  ","induk_provinsi":"Prov. Jawa Barat","kode_wilayah_induk_provinsi":"020000  ","bentuk_pendidikan":"SMK","status_sekolah":"Swasta","sinkron_terakhir":"20 Sep 2020 15:29:11","sekolah_id_enkrip":"98C5F843A703DDE413BC                                                                                "},{"nama":"SMKS YABP GARUT","sekolah_id":"A0494784-EEF6-4229-BD1C-C157C4D2ADD1","npsn":69753910,"jumlah_kirim":16,"ptk":11,"pegawai":6,"pd":210,"rombel":8,"jml_rk":7,"jml_lab":1,"jml_perpus":1,"induk_kecamatan":"Kec. Bungbulang","kode_wilayah_induk_kecamatan":"021103  ","induk_kabupaten":"Kab. Garut","kode_wilayah_induk_kabupaten":"021100  ","induk_provinsi":"Prov. Jawa Barat","kode_wilayah_induk_provinsi":"020000  ","bentuk_pendidikan":"SMK","status_sekolah":"Swasta","sinkron_terakhir":"24 Sep 2020 03:02:26","sekolah_id_enkrip":"9DC169F7EC45D7C7ACBE                                                                                "}]