[{"nama":"SMKS MIFTAHUL ULUM","sekolah_id":"57F8FE02-2035-4340-AB0F-5E7A21B8DD4B","npsn":20268845,"jumlah_kirim":28,"ptk":5,"pegawai":2,"pd":113,"rombel":4,"jml_rk":4,"jml_lab":1,"jml_perpus":1,"induk_kecamatan":"Kec. Gunungtanjung","kode_wilayah_induk_kecamatan":"021237  ","induk_kabupaten":"Kab. Tasikmalaya","kode_wilayah_induk_kabupaten":"021200  ","induk_provinsi":"Prov. Jawa Barat","kode_wilayah_induk_provinsi":"020000  ","bentuk_pendidikan":"SMK","status_sekolah":"Swasta","sinkron_terakhir":"01 Oct 2020 18:48:04","sekolah_id_enkrip":"2422FC2CB4662BDA41D9                                                                                "},{"nama":"SMKS PLUS AL HASANAH","sekolah_id":"842DA2C3-C19E-4F26-AE1B-A291393EE8E1","npsn":20268067,"jumlah_kirim":30,"ptk":37,"pegawai":7,"pd":634,"rombel":23,"jml_rk":21,"jml_lab":1,"jml_perpus":1,"induk_kecamatan":"Kec. Gunungtanjung","kode_wilayah_induk_kecamatan":"021237  ","induk_kabupaten":"Kab. Tasikmalaya","kode_wilayah_induk_kabupaten":"021200  ","induk_provinsi":"Prov. Jawa Barat","kode_wilayah_induk_provinsi":"020000  ","bentuk_pendidikan":"SMK","status_sekolah":"Swasta","sinkron_terakhir":"02 Oct 2020 10:45:56","sekolah_id_enkrip":"369DD31598FCF6597227                                                                                "}]