[{"nama":"SMK YAPENAS ","sekolah_id":"DA25B02D-FCA6-4F70-8C19-E67405690B32","npsn":69948128,"jumlah_kirim":20,"ptk":9,"pegawai":3,"pd":89,"rombel":4,"jml_rk":3,"jml_lab":0,"jml_perpus":0,"induk_kecamatan":"Kec. Klangenan","kode_wilayah_induk_kecamatan":"021719  ","induk_kabupaten":"Kab. Cirebon","kode_wilayah_induk_kabupaten":"021700  ","induk_provinsi":"Prov. Jawa Barat","kode_wilayah_induk_provinsi":"020000  ","bentuk_pendidikan":"SMK","status_sekolah":"Swasta","sinkron_terakhir":"24 Sep 2020 23:34:41","sekolah_id_enkrip":"6E074102C4E7CC5F0FC9                                                                                "}]