[{"nama":"SMKN 1 JATIBARANG","sekolah_id":"4A715993-B8D3-4D4E-B201-BBC7112B5A3F","npsn":20233761,"jumlah_kirim":26,"ptk":52,"pegawai":21,"pd":936,"rombel":32,"jml_rk":38,"jml_lab":1,"jml_perpus":1,"induk_kecamatan":"Kec. Jatibarang","kode_wilayah_induk_kecamatan":"021813  ","induk_kabupaten":"Kab. Indramayu","kode_wilayah_induk_kabupaten":"021800  ","induk_provinsi":"Prov. Jawa Barat","kode_wilayah_induk_provinsi":"020000  ","bentuk_pendidikan":"SMK","status_sekolah":"Negeri","sinkron_terakhir":"02 Oct 2020 08:38:39","sekolah_id_enkrip":"11B5A60B3D3B32EC7CC4                                                                                "},{"nama":"SMK PARIWISATA YAPPMI JATIBARANG","sekolah_id":"DF1BEA26-62FE-45F1-88B8-588C82C94610","npsn":69948195,"jumlah_kirim":52,"ptk":19,"pegawai":7,"pd":175,"rombel":9,"jml_rk":9,"jml_lab":2,"jml_perpus":1,"induk_kecamatan":"Kec. Jatibarang","kode_wilayah_induk_kecamatan":"021813  ","induk_kabupaten":"Kab. Indramayu","kode_wilayah_induk_kabupaten":"021800  ","induk_provinsi":"Prov. Jawa Barat","kode_wilayah_induk_provinsi":"020000  ","bentuk_pendidikan":"SMK","status_sekolah":"Swasta","sinkron_terakhir":"02 Oct 2020 10:14:29","sekolah_id_enkrip":"0B5437478C685D04C7B0                                                                                "},{"nama":"SMKS AS-SALAAM JATIBARANG ","sekolah_id":"EB0C7BF4-D9BD-46F5-B984-9670168EF14E","npsn":69734355,"jumlah_kirim":75,"ptk":26,"pegawai":7,"pd":254,"rombel":12,"jml_rk":12,"jml_lab":2,"jml_perpus":1,"induk_kecamatan":"Kec. Jatibarang","kode_wilayah_induk_kecamatan":"021813  ","induk_kabupaten":"Kab. Indramayu","kode_wilayah_induk_kabupaten":"021800  ","induk_provinsi":"Prov. Jawa Barat","kode_wilayah_induk_provinsi":"020000  ","bentuk_pendidikan":"SMK","status_sekolah":"Swasta","sinkron_terakhir":"24 Sep 2020 09:12:01","sekolah_id_enkrip":"BB5EB22E91B75F0CE289                                                                                "},{"nama":"SMKS MUHAMMADIYAH JATIBARANG","sekolah_id":"2847D893-931D-47ED-AE61-D86018F7B3A1","npsn":20252980,"jumlah_kirim":61,"ptk":14,"pegawai":2,"pd":240,"rombel":8,"jml_rk":6,"jml_lab":2,"jml_perpus":1,"induk_kecamatan":"Kec. Jatibarang","kode_wilayah_induk_kecamatan":"021813  ","induk_kabupaten":"Kab. Indramayu","kode_wilayah_induk_kabupaten":"021800  ","induk_provinsi":"Prov. Jawa Barat","kode_wilayah_induk_provinsi":"020000  ","bentuk_pendidikan":"SMK","status_sekolah":"Swasta","sinkron_terakhir":"02 Oct 2020 10:52:04","sekolah_id_enkrip":"E4D8D79FBC5DEBA70E54                                                                                "},{"nama":"SMKS PELITA JATIBARANG","sekolah_id":"729D4A0F-EEA9-4C59-93FD-C0302119051E","npsn":20215994,"jumlah_kirim":18,"ptk":27,"pegawai":7,"pd":701,"rombel":24,"jml_rk":24,"jml_lab":1,"jml_perpus":1,"induk_kecamatan":"Kec. Jatibarang","kode_wilayah_induk_kecamatan":"021813  ","induk_kabupaten":"Kab. Indramayu","kode_wilayah_induk_kabupaten":"021800  ","induk_provinsi":"Prov. Jawa Barat","kode_wilayah_induk_provinsi":"020000  ","bentuk_pendidikan":"SMK","status_sekolah":"Swasta","sinkron_terakhir":"29 Sep 2020 08:52:51","sekolah_id_enkrip":"078218B2B73E0EA906F5                                                                                "},{"nama":"SMKS PGRI JATIBARANG","sekolah_id":"53D7C796-569F-4E2A-BD71-AF42B7C8699A","npsn":20215971,"jumlah_kirim":167,"ptk":56,"pegawai":19,"pd":1712,"rombel":46,"jml_rk":45,"jml_lab":2,"jml_perpus":1,"induk_kecamatan":"Kec. Jatibarang","kode_wilayah_induk_kecamatan":"021813  ","induk_kabupaten":"Kab. Indramayu","kode_wilayah_induk_kabupaten":"021800  ","induk_provinsi":"Prov. Jawa Barat","kode_wilayah_induk_provinsi":"020000  ","bentuk_pendidikan":"SMK","status_sekolah":"Swasta","sinkron_terakhir":"02 Oct 2020 11:19:25","sekolah_id_enkrip":"747DAC4790CE508ECB6E                                                                                "},{"nama":"SMKS PUI JATIBARANG","sekolah_id":"7E258F47-F39A-4D2C-B4A3-0FBBDE6B92CB","npsn":20215948,"jumlah_kirim":19,"ptk":24,"pegawai":8,"pd":550,"rombel":19,"jml_rk":19,"jml_lab":0,"jml_perpus":1,"induk_kecamatan":"Kec. Jatibarang","kode_wilayah_induk_kecamatan":"021813  ","induk_kabupaten":"Kab. Indramayu","kode_wilayah_induk_kabupaten":"021800  ","induk_provinsi":"Prov. Jawa Barat","kode_wilayah_induk_provinsi":"020000  ","bentuk_pendidikan":"SMK","status_sekolah":"Swasta","sinkron_terakhir":"08 Sep 2020 12:40:10","sekolah_id_enkrip":"9358FB2E712423439818                                                                                "}]