[{"nama":"SMK NEGERI CIJAMBE","sekolah_id":"78442D04-7702-4D95-B49F-A8388A1D2FB1","npsn":69877402,"jumlah_kirim":27,"ptk":21,"pegawai":3,"pd":127,"rombel":11,"jml_rk":13,"jml_lab":1,"jml_perpus":1,"induk_kecamatan":"Kec. Cijambe","kode_wilayah_induk_kecamatan":"021905  ","induk_kabupaten":"Kab. Subang","kode_wilayah_induk_kabupaten":"021900  ","induk_provinsi":"Prov. Jawa Barat","kode_wilayah_induk_provinsi":"020000  ","bentuk_pendidikan":"SMK","status_sekolah":"Negeri","sinkron_terakhir":"24 Sep 2020 06:20:32","sekolah_id_enkrip":"332588F00F0F680A149F                                                                                "},{"nama":"SMK CIMENTENG","sekolah_id":"FEEC21E8-220C-4A94-B660-0C492924877F","npsn":69875558,"jumlah_kirim":1,"ptk":null,"pegawai":null,"pd":24,"rombel":3,"jml_rk":3,"jml_lab":1,"jml_perpus":1,"induk_kecamatan":"Kec. Cijambe","kode_wilayah_induk_kecamatan":"021905  ","induk_kabupaten":"Kab. Subang","kode_wilayah_induk_kabupaten":"021900  ","induk_provinsi":"Prov. Jawa Barat","kode_wilayah_induk_provinsi":"020000  ","bentuk_pendidikan":"SMK","status_sekolah":"Swasta","sinkron_terakhir":"27 Aug 2020 16:51:37","sekolah_id_enkrip":"940CE1C122394719C99F                                                                                "},{"nama":"SMK ISLAM CIBULUH","sekolah_id":"96D0CC76-3FA1-4D1D-BB4A-5807C85D7B36","npsn":69875552,"jumlah_kirim":6,"ptk":1,"pegawai":1,"pd":35,"rombel":3,"jml_rk":3,"jml_lab":0,"jml_perpus":1,"induk_kecamatan":"Kec. Cijambe","kode_wilayah_induk_kecamatan":"021905  ","induk_kabupaten":"Kab. Subang","kode_wilayah_induk_kabupaten":"021900  ","induk_provinsi":"Prov. Jawa Barat","kode_wilayah_induk_provinsi":"020000  ","bentuk_pendidikan":"SMK","status_sekolah":"Swasta","sinkron_terakhir":"11 Sep 2020 12:53:45","sekolah_id_enkrip":"FC2D8ED4EA93C82A1F7D                                                                                "},{"nama":"SMK ISLAM CIKADU","sekolah_id":"6215F50B-95DD-4021-A1CE-78B5290B7FEA","npsn":69875553,"jumlah_kirim":15,"ptk":2,"pegawai":1,"pd":31,"rombel":3,"jml_rk":3,"jml_lab":1,"jml_perpus":1,"induk_kecamatan":"Kec. Cijambe","kode_wilayah_induk_kecamatan":"021905  ","induk_kabupaten":"Kab. Subang","kode_wilayah_induk_kabupaten":"021900  ","induk_provinsi":"Prov. Jawa Barat","kode_wilayah_induk_provinsi":"020000  ","bentuk_pendidikan":"SMK","status_sekolah":"Swasta","sinkron_terakhir":"24 Sep 2020 17:17:24","sekolah_id_enkrip":"C7807DEC604B48C0745D                                                                                "},{"nama":"SMKS RIYADHUL JANNAH CIJAMBE","sekolah_id":"60923DDC-923F-4077-AE29-AD0DB8A451F1","npsn":20233690,"jumlah_kirim":31,"ptk":6,"pegawai":0,"pd":111,"rombel":3,"jml_rk":5,"jml_lab":1,"jml_perpus":1,"induk_kecamatan":"Kec. Cijambe","kode_wilayah_induk_kecamatan":"021905  ","induk_kabupaten":"Kab. Subang","kode_wilayah_induk_kabupaten":"021900  ","induk_provinsi":"Prov. Jawa Barat","kode_wilayah_induk_provinsi":"020000  ","bentuk_pendidikan":"SMK","status_sekolah":"Swasta","sinkron_terakhir":"25 Sep 2020 14:17:50","sekolah_id_enkrip":"612370A54FC7D4892E5C                                                                                "}]