[{"nama":"SMK CENDEKIA BATUJAJAR","sekolah_id":"67C259E3-7DB0-4717-947F-8DE38140B84D","npsn":69946965,"jumlah_kirim":28,"ptk":35,"pegawai":10,"pd":829,"rombel":25,"jml_rk":26,"jml_lab":1,"jml_perpus":1,"induk_kecamatan":"Kec. Batujajar","kode_wilayah_induk_kecamatan":"022307  ","induk_kabupaten":"Kab. Bandung Barat","kode_wilayah_induk_kabupaten":"022300  ","induk_provinsi":"Prov. Jawa Barat","kode_wilayah_induk_provinsi":"020000  ","bentuk_pendidikan":"SMK","status_sekolah":"Swasta","sinkron_terakhir":"02 Oct 2020 09:41:18","sekolah_id_enkrip":"AA29561191D8E4E54C05                                                                                "},{"nama":"SMKS AL IHSAN BATUJAJAR","sekolah_id":"F8A1B679-E830-46CA-8239-B6550DDF6702","npsn":20268293,"jumlah_kirim":13,"ptk":9,"pegawai":1,"pd":192,"rombel":7,"jml_rk":9,"jml_lab":3,"jml_perpus":1,"induk_kecamatan":"Kec. Batujajar","kode_wilayah_induk_kecamatan":"022307  ","induk_kabupaten":"Kab. Bandung Barat","kode_wilayah_induk_kabupaten":"022300  ","induk_provinsi":"Prov. Jawa Barat","kode_wilayah_induk_provinsi":"020000  ","bentuk_pendidikan":"SMK","status_sekolah":"Swasta","sinkron_terakhir":"22 Sep 2020 22:09:04","sekolah_id_enkrip":"266CF7900F991B45E986                                                                                "},{"nama":"SMKS DHARMA BHAKTI INDONESIA","sekolah_id":"E271C2C5-693A-4EE4-AE44-E5C8B82CD035","npsn":69728242,"jumlah_kirim":33,"ptk":11,"pegawai":4,"pd":450,"rombel":14,"jml_rk":9,"jml_lab":3,"jml_perpus":1,"induk_kecamatan":"Kec. Batujajar","kode_wilayah_induk_kecamatan":"022307  ","induk_kabupaten":"Kab. Bandung Barat","kode_wilayah_induk_kabupaten":"022300  ","induk_provinsi":"Prov. Jawa Barat","kode_wilayah_induk_provinsi":"020000  ","bentuk_pendidikan":"SMK","status_sekolah":"Swasta","sinkron_terakhir":"29 Sep 2020 09:01:53","sekolah_id_enkrip":"49BCE9176CA9D6E9E6D4                                                                                "},{"nama":"SMKS JABIR AL HAYYAN","sekolah_id":"A1F56CF2-F478-4052-A343-37C66AB1E6D1","npsn":20268296,"jumlah_kirim":58,"ptk":8,"pegawai":2,"pd":93,"rombel":4,"jml_rk":4,"jml_lab":3,"jml_perpus":1,"induk_kecamatan":"Kec. Batujajar","kode_wilayah_induk_kecamatan":"022307  ","induk_kabupaten":"Kab. Bandung Barat","kode_wilayah_induk_kabupaten":"022300  ","induk_provinsi":"Prov. Jawa Barat","kode_wilayah_induk_provinsi":"020000  ","bentuk_pendidikan":"SMK","status_sekolah":"Swasta","sinkron_terakhir":"02 Sep 2020 20:04:26","sekolah_id_enkrip":"CF77CBFAA67FDB3744BF                                                                                "},{"nama":"SMKS KESFAM BATUJAJAR","sekolah_id":"6C9E69BA-89B3-4B97-8D1A-76F57F4086BE","npsn":69733996,"jumlah_kirim":80,"ptk":12,"pegawai":1,"pd":132,"rombel":7,"jml_rk":4,"jml_lab":1,"jml_perpus":1,"induk_kecamatan":"Kec. Batujajar","kode_wilayah_induk_kecamatan":"022307  ","induk_kabupaten":"Kab. Bandung Barat","kode_wilayah_induk_kabupaten":"022300  ","induk_provinsi":"Prov. Jawa Barat","kode_wilayah_induk_provinsi":"020000  ","bentuk_pendidikan":"SMK","status_sekolah":"Swasta","sinkron_terakhir":"02 Oct 2020 08:35:21","sekolah_id_enkrip":"CB892597E760F8A7F703                                                                                "},{"nama":"SMKS LUHUR BALADIKA","sekolah_id":"6D246DBD-6CBB-4F52-B59A-85943823930B","npsn":69733857,"jumlah_kirim":6,"ptk":8,"pegawai":1,"pd":81,"rombel":7,"jml_rk":8,"jml_lab":1,"jml_perpus":1,"induk_kecamatan":"Kec. Batujajar","kode_wilayah_induk_kecamatan":"022307  ","induk_kabupaten":"Kab. Bandung Barat","kode_wilayah_induk_kabupaten":"022300  ","induk_provinsi":"Prov. Jawa Barat","kode_wilayah_induk_provinsi":"020000  ","bentuk_pendidikan":"SMK","status_sekolah":"Swasta","sinkron_terakhir":"24 Aug 2020 17:53:34","sekolah_id_enkrip":"5CD908F33E24108345FB                                                                                "},{"nama":"SMKS MAHARDHIKA BATUJAJAR","sekolah_id":"C1ADCA95-F6B3-40D3-BA6B-09F2081A186A","npsn":20227955,"jumlah_kirim":49,"ptk":55,"pegawai":5,"pd":1381,"rombel":42,"jml_rk":44,"jml_lab":3,"jml_perpus":1,"induk_kecamatan":"Kec. Batujajar","kode_wilayah_induk_kecamatan":"022307  ","induk_kabupaten":"Kab. Bandung Barat","kode_wilayah_induk_kabupaten":"022300  ","induk_provinsi":"Prov. Jawa Barat","kode_wilayah_induk_provinsi":"020000  ","bentuk_pendidikan":"SMK","status_sekolah":"Swasta","sinkron_terakhir":"02 Oct 2020 08:57:58","sekolah_id_enkrip":"157980BFCE1EEB580056                                                                                "},{"nama":"SMKS PASUNDAN PERKASA DAARUL HIDAYAH","sekolah_id":"39BB7CCD-9285-4133-AA7B-58BD656F3BA1","npsn":69830696,"jumlah_kirim":16,"ptk":7,"pegawai":4,"pd":64,"rombel":6,"jml_rk":5,"jml_lab":0,"jml_perpus":1,"induk_kecamatan":"Kec. Batujajar","kode_wilayah_induk_kecamatan":"022307  ","induk_kabupaten":"Kab. Bandung Barat","kode_wilayah_induk_kabupaten":"022300  ","induk_provinsi":"Prov. Jawa Barat","kode_wilayah_induk_provinsi":"020000  ","bentuk_pendidikan":"SMK","status_sekolah":"Swasta","sinkron_terakhir":"28 Sep 2020 09:34:45","sekolah_id_enkrip":"735C82620C64F3351952                                                                                "}]