[{"nama":"SMKN 4 SUKABUMI","sekolah_id":"9ABAAEC4-A00E-4976-A02B-550F70C8BC4D","npsn":20253907,"jumlah_kirim":18,"ptk":54,"pegawai":24,"pd":1497,"rombel":43,"jml_rk":39,"jml_lab":0,"jml_perpus":1,"induk_kecamatan":"Kec. Lembur Situ","kode_wilayah_induk_kecamatan":"026206  ","induk_kabupaten":"Kota Sukabumi","kode_wilayah_induk_kabupaten":"026200  ","induk_provinsi":"Prov. Jawa Barat","kode_wilayah_induk_provinsi":"020000  ","bentuk_pendidikan":"SMK","status_sekolah":"Negeri","sinkron_terakhir":"29 Sep 2020 15:43:11","sekolah_id_enkrip":"A7EC18F3517CFBB7A855                                                                                "},{"nama":"SMK IT AMAL ISLAMI","sekolah_id":"D9C5E97A-AFB0-45A2-AE14-A67A588EC48E","npsn":69899673,"jumlah_kirim":8,"ptk":7,"pegawai":3,"pd":34,"rombel":3,"jml_rk":3,"jml_lab":1,"jml_perpus":1,"induk_kecamatan":"Kec. Lembur Situ","kode_wilayah_induk_kecamatan":"026206  ","induk_kabupaten":"Kota Sukabumi","kode_wilayah_induk_kabupaten":"026200  ","induk_provinsi":"Prov. Jawa Barat","kode_wilayah_induk_provinsi":"020000  ","bentuk_pendidikan":"SMK","status_sekolah":"Swasta","sinkron_terakhir":"15 Sep 2020 05:46:37","sekolah_id_enkrip":"5761A225635037178967                                                                                "},{"nama":"SMKS BINA SATYA MANDIRI","sekolah_id":"ED935B03-D5BA-42CD-9E18-72C439FB3E64","npsn":69757152,"jumlah_kirim":10,"ptk":9,"pegawai":3,"pd":163,"rombel":6,"jml_rk":5,"jml_lab":1,"jml_perpus":1,"induk_kecamatan":"Kec. Lembur Situ","kode_wilayah_induk_kecamatan":"026206  ","induk_kabupaten":"Kota Sukabumi","kode_wilayah_induk_kabupaten":"026200  ","induk_provinsi":"Prov. Jawa Barat","kode_wilayah_induk_provinsi":"020000  ","bentuk_pendidikan":"SMK","status_sekolah":"Swasta","sinkron_terakhir":"01 Oct 2020 08:25:28","sekolah_id_enkrip":"829249616E85BD0C03B4                                                                                "},{"nama":"SMKS KESEHATAN TUNAS MADANI","sekolah_id":"01E6D945-F2EA-4894-8867-3BC43DF8D807","npsn":69757213,"jumlah_kirim":47,"ptk":10,"pegawai":2,"pd":355,"rombel":10,"jml_rk":10,"jml_lab":1,"jml_perpus":1,"induk_kecamatan":"Kec. Lembur Situ","kode_wilayah_induk_kecamatan":"026206  ","induk_kabupaten":"Kota Sukabumi","kode_wilayah_induk_kabupaten":"026200  ","induk_provinsi":"Prov. Jawa Barat","kode_wilayah_induk_provinsi":"020000  ","bentuk_pendidikan":"SMK","status_sekolah":"Swasta","sinkron_terakhir":"08 Sep 2020 06:04:06","sekolah_id_enkrip":"84AAFA3D80FB0B9041D3                                                                                "},{"nama":"SMKS PLUS BINA TEKNIK YLPI SUKABUMI","sekolah_id":"88346DAF-62B4-41F2-99A9-9B8E86E0292D","npsn":20221595,"jumlah_kirim":48,"ptk":12,"pegawai":3,"pd":246,"rombel":9,"jml_rk":11,"jml_lab":2,"jml_perpus":1,"induk_kecamatan":"Kec. Lembur Situ","kode_wilayah_induk_kecamatan":"026206  ","induk_kabupaten":"Kota Sukabumi","kode_wilayah_induk_kabupaten":"026200  ","induk_provinsi":"Prov. Jawa Barat","kode_wilayah_induk_provinsi":"020000  ","bentuk_pendidikan":"SMK","status_sekolah":"Swasta","sinkron_terakhir":"16 Sep 2020 09:26:41","sekolah_id_enkrip":"507EA205763E9A206B5E                                                                                "},{"nama":"SMKS TERPADU IBADURRAHMAN","sekolah_id":"B092A449-6EAB-41D7-8AB2-B9C587F6061C","npsn":20265663,"jumlah_kirim":40,"ptk":19,"pegawai":4,"pd":556,"rombel":15,"jml_rk":13,"jml_lab":1,"jml_perpus":1,"induk_kecamatan":"Kec. Lembur Situ","kode_wilayah_induk_kecamatan":"026206  ","induk_kabupaten":"Kota Sukabumi","kode_wilayah_induk_kabupaten":"026200  ","induk_provinsi":"Prov. Jawa Barat","kode_wilayah_induk_provinsi":"020000  ","bentuk_pendidikan":"SMK","status_sekolah":"Swasta","sinkron_terakhir":"15 Sep 2020 12:21:18","sekolah_id_enkrip":"696959DC450CA718EBAF                                                                                "}]