[{"nama":"SMK PRESIDEN CIREBON","sekolah_id":"8149C899-9FEF-405B-ACBC-CB5626A4F0B5","npsn":69929094,"jumlah_kirim":50,"ptk":31,"pegawai":4,"pd":498,"rombel":17,"jml_rk":18,"jml_lab":2,"jml_perpus":1,"induk_kecamatan":"Kec. Lemahwungkuk","kode_wilayah_induk_kecamatan":"026302  ","induk_kabupaten":"Kota Cirebon","kode_wilayah_induk_kabupaten":"026300  ","induk_provinsi":"Prov. Jawa Barat","kode_wilayah_induk_provinsi":"020000  ","bentuk_pendidikan":"SMK","status_sekolah":"Swasta","sinkron_terakhir":"29 Sep 2020 14:23:33","sekolah_id_enkrip":"CAA2B81E2D72DB9EB3FC                                                                                "},{"nama":"SMKS MUHAMMADIYAH KOTA CIREBON","sekolah_id":"B827BD03-7AB4-4836-994F-D16D4224B93D","npsn":20253885,"jumlah_kirim":36,"ptk":27,"pegawai":6,"pd":243,"rombel":12,"jml_rk":16,"jml_lab":1,"jml_perpus":1,"induk_kecamatan":"Kec. Lemahwungkuk","kode_wilayah_induk_kecamatan":"026302  ","induk_kabupaten":"Kota Cirebon","kode_wilayah_induk_kabupaten":"026300  ","induk_provinsi":"Prov. Jawa Barat","kode_wilayah_induk_provinsi":"020000  ","bentuk_pendidikan":"SMK","status_sekolah":"Swasta","sinkron_terakhir":"21 Sep 2020 14:03:24","sekolah_id_enkrip":"A26A4C65DDEBAD3FD107                                                                                "},{"nama":"SMKS NAHDLATUL ULAMA","sekolah_id":"BEEEF79C-69A1-4AF4-A008-61C9ECB3DFC2","npsn":69771422,"jumlah_kirim":21,"ptk":11,"pegawai":5,"pd":47,"rombel":6,"jml_rk":6,"jml_lab":2,"jml_perpus":1,"induk_kecamatan":"Kec. Lemahwungkuk","kode_wilayah_induk_kecamatan":"026302  ","induk_kabupaten":"Kota Cirebon","kode_wilayah_induk_kabupaten":"026300  ","induk_provinsi":"Prov. Jawa Barat","kode_wilayah_induk_provinsi":"020000  ","bentuk_pendidikan":"SMK","status_sekolah":"Swasta","sinkron_terakhir":"02 Oct 2020 09:28:49","sekolah_id_enkrip":"5534298C9AC249C8F3EC                                                                                "},{"nama":"SMKS PAKUNGWATI CIREBON","sekolah_id":"2D1D631A-5F36-4E81-A3E0-C5FC28B2199B","npsn":20222177,"jumlah_kirim":7,"ptk":7,"pegawai":1,"pd":16,"rombel":3,"jml_rk":3,"jml_lab":1,"jml_perpus":1,"induk_kecamatan":"Kec. Lemahwungkuk","kode_wilayah_induk_kecamatan":"026302  ","induk_kabupaten":"Kota Cirebon","kode_wilayah_induk_kabupaten":"026300  ","induk_provinsi":"Prov. Jawa Barat","kode_wilayah_induk_provinsi":"020000  ","bentuk_pendidikan":"SMK","status_sekolah":"Swasta","sinkron_terakhir":"26 Sep 2020 21:20:58","sekolah_id_enkrip":"CA85FCD7DAEC87840185                                                                                "},{"nama":"SMKS TEKNIK PERKAPALAN","sekolah_id":"51179A75-53C6-442C-85F2-A70E33BE8FFD","npsn":60726461,"jumlah_kirim":null,"ptk":null,"pegawai":null,"pd":null,"rombel":null,"jml_rk":3,"jml_lab":0,"jml_perpus":1,"induk_kecamatan":"Kec. Lemahwungkuk","kode_wilayah_induk_kecamatan":"026302  ","induk_kabupaten":"Kota Cirebon","kode_wilayah_induk_kabupaten":"026300  ","induk_provinsi":"Prov. Jawa Barat","kode_wilayah_induk_provinsi":"020000  ","bentuk_pendidikan":"SMK","status_sekolah":"Swasta","sinkron_terakhir":null,"sekolah_id_enkrip":"4B8C4F3F3A53846EE2AC                                                                                "}]