[{"nama":"SMKN 1 BREBES","sekolah_id":"4B2F9D61-3FB5-449D-8FF1-83027A3DC4CE","npsn":20326427,"jumlah_kirim":231,"ptk":62,"pegawai":22,"pd":1392,"rombel":39,"jml_rk":39,"jml_lab":1,"jml_perpus":1,"induk_kecamatan":"Kec. Brebes","kode_wilayah_induk_kecamatan":"032917  ","induk_kabupaten":"Kab. Brebes","kode_wilayah_induk_kabupaten":"032900  ","induk_provinsi":"Prov. Jawa Tengah","kode_wilayah_induk_provinsi":"030000  ","bentuk_pendidikan":"SMK","status_sekolah":"Negeri","sinkron_terakhir":"02 Oct 2020 06:58:07","sekolah_id_enkrip":"0FA10BC04AB265B557ED                                                                                "},{"nama":"SMK BOARDING SCHOOL BREBES","sekolah_id":"1CADC9D4-363B-46CF-9804-44BCBEE759F2","npsn":69895515,"jumlah_kirim":11,"ptk":11,"pegawai":3,"pd":184,"rombel":7,"jml_rk":7,"jml_lab":1,"jml_perpus":1,"induk_kecamatan":"Kec. Brebes","kode_wilayah_induk_kecamatan":"032917  ","induk_kabupaten":"Kab. Brebes","kode_wilayah_induk_kabupaten":"032900  ","induk_provinsi":"Prov. Jawa Tengah","kode_wilayah_induk_provinsi":"030000  ","bentuk_pendidikan":"SMK","status_sekolah":"Swasta","sinkron_terakhir":"22 Sep 2020 10:12:27","sekolah_id_enkrip":"527F1F573627B33949E0                                                                                "},{"nama":"SMKS AGRIBISNIS","sekolah_id":"4C508D0C-8953-440A-BA56-766FCB46C540","npsn":20362809,"jumlah_kirim":6,"ptk":5,"pegawai":1,"pd":36,"rombel":3,"jml_rk":3,"jml_lab":1,"jml_perpus":1,"induk_kecamatan":"Kec. Brebes","kode_wilayah_induk_kecamatan":"032917  ","induk_kabupaten":"Kab. Brebes","kode_wilayah_induk_kabupaten":"032900  ","induk_provinsi":"Prov. Jawa Tengah","kode_wilayah_induk_provinsi":"030000  ","bentuk_pendidikan":"SMK","status_sekolah":"Swasta","sinkron_terakhir":"02 Sep 2020 01:03:03","sekolah_id_enkrip":"18817713DCE9133E2F13                                                                                "},{"nama":"SMKS BUDI UTOMO BREBES","sekolah_id":"0C0F8313-3177-4154-B3E0-B961F67046A3","npsn":20340786,"jumlah_kirim":null,"ptk":null,"pegawai":null,"pd":null,"rombel":null,"jml_rk":4,"jml_lab":1,"jml_perpus":1,"induk_kecamatan":"Kec. Brebes","kode_wilayah_induk_kecamatan":"032917  ","induk_kabupaten":"Kab. Brebes","kode_wilayah_induk_kabupaten":"032900  ","induk_provinsi":"Prov. Jawa Tengah","kode_wilayah_induk_provinsi":"030000  ","bentuk_pendidikan":"SMK","status_sekolah":"Swasta","sinkron_terakhir":null,"sekolah_id_enkrip":"E5D7BD94CAD4465E5B04                                                                                "},{"nama":"SMKS CAKRA NENGGALA BREBES","sekolah_id":"6BA0D924-DCFA-4A7C-8535-5C125BD072A5","npsn":69845535,"jumlah_kirim":47,"ptk":11,"pegawai":2,"pd":88,"rombel":4,"jml_rk":3,"jml_lab":1,"jml_perpus":1,"induk_kecamatan":"Kec. Brebes","kode_wilayah_induk_kecamatan":"032917  ","induk_kabupaten":"Kab. Brebes","kode_wilayah_induk_kabupaten":"032900  ","induk_provinsi":"Prov. Jawa Tengah","kode_wilayah_induk_provinsi":"030000  ","bentuk_pendidikan":"SMK","status_sekolah":"Swasta","sinkron_terakhir":"13 Sep 2020 18:33:36","sekolah_id_enkrip":"FCEA1BCEED9C86088C4A                                                                                "},{"nama":"SMKS FARMASI YPIB BREBES","sekolah_id":"8AE202CB-BEED-4BD2-8F4A-19E88A1F98C6","npsn":20350726,"jumlah_kirim":17,"ptk":18,"pegawai":8,"pd":219,"rombel":9,"jml_rk":9,"jml_lab":1,"jml_perpus":1,"induk_kecamatan":"Kec. Brebes","kode_wilayah_induk_kecamatan":"032917  ","induk_kabupaten":"Kab. Brebes","kode_wilayah_induk_kabupaten":"032900  ","induk_provinsi":"Prov. Jawa Tengah","kode_wilayah_induk_provinsi":"030000  ","bentuk_pendidikan":"SMK","status_sekolah":"Swasta","sinkron_terakhir":"31 Aug 2020 17:06:55","sekolah_id_enkrip":"221C060272704D408B6A                                                                                "},{"nama":"SMKS IC ISLAMIC CENTRE","sekolah_id":"4EE16246-B887-43AB-AD13-046587669F33","npsn":69854735,"jumlah_kirim":31,"ptk":12,"pegawai":3,"pd":63,"rombel":6,"jml_rk":9,"jml_lab":2,"jml_perpus":1,"induk_kecamatan":"Kec. Brebes","kode_wilayah_induk_kecamatan":"032917  ","induk_kabupaten":"Kab. Brebes","kode_wilayah_induk_kabupaten":"032900  ","induk_provinsi":"Prov. Jawa Tengah","kode_wilayah_induk_provinsi":"030000  ","bentuk_pendidikan":"SMK","status_sekolah":"Swasta","sinkron_terakhir":"01 Oct 2020 11:09:51","sekolah_id_enkrip":"E4C68E7F102A890EC582                                                                                "},{"nama":"SMKS KARYA BHAKTI BREBES","sekolah_id":"0EA00FC8-6D4C-4A3B-9554-69F2FF940180","npsn":20326423,"jumlah_kirim":49,"ptk":73,"pegawai":26,"pd":1385,"rombel":41,"jml_rk":41,"jml_lab":4,"jml_perpus":1,"induk_kecamatan":"Kec. Brebes","kode_wilayah_induk_kecamatan":"032917  ","induk_kabupaten":"Kab. Brebes","kode_wilayah_induk_kabupaten":"032900  ","induk_provinsi":"Prov. Jawa Tengah","kode_wilayah_induk_provinsi":"030000  ","bentuk_pendidikan":"SMK","status_sekolah":"Swasta","sinkron_terakhir":"29 Sep 2020 11:41:51","sekolah_id_enkrip":"242FF237302460C8C1F6                                                                                "},{"nama":"SMKS MADANI BREBES","sekolah_id":"D73C26D5-238E-4104-A4EE-52DB9419467F","npsn":69761921,"jumlah_kirim":56,"ptk":16,"pegawai":7,"pd":191,"rombel":8,"jml_rk":10,"jml_lab":1,"jml_perpus":1,"induk_kecamatan":"Kec. Brebes","kode_wilayah_induk_kecamatan":"032917  ","induk_kabupaten":"Kab. Brebes","kode_wilayah_induk_kabupaten":"032900  ","induk_provinsi":"Prov. Jawa Tengah","kode_wilayah_induk_provinsi":"030000  ","bentuk_pendidikan":"SMK","status_sekolah":"Swasta","sinkron_terakhir":"02 Oct 2020 08:52:16","sekolah_id_enkrip":"3734275DEC5566311B27                                                                                "},{"nama":"SMKS PGRI BREBES","sekolah_id":"00564FAD-CAF4-4BC3-823A-050E7CF6B9BD","npsn":69763262,"jumlah_kirim":44,"ptk":23,"pegawai":12,"pd":334,"rombel":14,"jml_rk":14,"jml_lab":2,"jml_perpus":1,"induk_kecamatan":"Kec. Brebes","kode_wilayah_induk_kecamatan":"032917  ","induk_kabupaten":"Kab. Brebes","kode_wilayah_induk_kabupaten":"032900  ","induk_provinsi":"Prov. Jawa Tengah","kode_wilayah_induk_provinsi":"030000  ","bentuk_pendidikan":"SMK","status_sekolah":"Swasta","sinkron_terakhir":"30 Sep 2020 12:23:07","sekolah_id_enkrip":"A8ABDDE0E3506DD7164C                                                                                "},{"nama":"SMKS PUSPONEGORO 01 BREBES","sekolah_id":"DD1C2167-17DC-405F-B909-2D41E686D6A8","npsn":20326459,"jumlah_kirim":61,"ptk":27,"pegawai":14,"pd":427,"rombel":19,"jml_rk":18,"jml_lab":1,"jml_perpus":1,"induk_kecamatan":"Kec. Brebes","kode_wilayah_induk_kecamatan":"032917  ","induk_kabupaten":"Kab. Brebes","kode_wilayah_induk_kabupaten":"032900  ","induk_provinsi":"Prov. Jawa Tengah","kode_wilayah_induk_provinsi":"030000  ","bentuk_pendidikan":"SMK","status_sekolah":"Swasta","sinkron_terakhir":"30 Sep 2020 12:28:41","sekolah_id_enkrip":"F4A08A1EB300E55308EB                                                                                "}]