[{"nama":"SMK HASAN JUFRI BAWEAN","sekolah_id":"23504EA0-D258-4BE6-90AB-20DEF4940471","npsn":69965818,"jumlah_kirim":39,"ptk":7,"pegawai":1,"pd":134,"rombel":7,"jml_rk":8,"jml_lab":1,"jml_perpus":1,"induk_kecamatan":"Kec. Sangkapura","kode_wilayah_induk_kecamatan":"050117  ","induk_kabupaten":"Kab. Gresik","kode_wilayah_induk_kabupaten":"050100  ","induk_provinsi":"Prov. Jawa Timur","kode_wilayah_induk_provinsi":"050000  ","bentuk_pendidikan":"SMK","status_sekolah":"Swasta","sinkron_terakhir":"19 Sep 2020 23:39:20","sekolah_id_enkrip":"1D03796EE9C36CCB6910                                                                                "},{"nama":"SMK MUHAMMADIYAH 4 SANGKAPURA","sekolah_id":"855F51A9-C9DA-407D-8172-C33CB3E2B10A","npsn":69877320,"jumlah_kirim":24,"ptk":7,"pegawai":2,"pd":77,"rombel":6,"jml_rk":6,"jml_lab":1,"jml_perpus":1,"induk_kecamatan":"Kec. Sangkapura","kode_wilayah_induk_kecamatan":"050117  ","induk_kabupaten":"Kab. Gresik","kode_wilayah_induk_kabupaten":"050100  ","induk_provinsi":"Prov. Jawa Timur","kode_wilayah_induk_provinsi":"050000  ","bentuk_pendidikan":"SMK","status_sekolah":"Swasta","sinkron_terakhir":"24 Sep 2020 06:04:50","sekolah_id_enkrip":"616BC13BA9F3432F8F91                                                                                "},{"nama":"SMK QIRAATUT THALIBIN","sekolah_id":"48FCFD5C-128E-41A6-B26F-A51D078C0037","npsn":69843550,"jumlah_kirim":16,"ptk":0,"pegawai":1,"pd":46,"rombel":3,"jml_rk":3,"jml_lab":1,"jml_perpus":1,"induk_kecamatan":"Kec. Sangkapura","kode_wilayah_induk_kecamatan":"050117  ","induk_kabupaten":"Kab. Gresik","kode_wilayah_induk_kabupaten":"050100  ","induk_provinsi":"Prov. Jawa Timur","kode_wilayah_induk_provinsi":"050000  ","bentuk_pendidikan":"SMK","status_sekolah":"Swasta","sinkron_terakhir":"29 Aug 2020 16:37:29","sekolah_id_enkrip":"4E509E96CBE33B10C195                                                                                "},{"nama":"SMK UMAR MASUD","sekolah_id":"CD19314B-DA72-457F-B103-735A90A5B275","npsn":69888997,"jumlah_kirim":61,"ptk":9,"pegawai":2,"pd":75,"rombel":3,"jml_rk":5,"jml_lab":3,"jml_perpus":1,"induk_kecamatan":"Kec. Sangkapura","kode_wilayah_induk_kecamatan":"050117  ","induk_kabupaten":"Kab. Gresik","kode_wilayah_induk_kabupaten":"050100  ","induk_provinsi":"Prov. Jawa Timur","kode_wilayah_induk_provinsi":"050000  ","bentuk_pendidikan":"SMK","status_sekolah":"Swasta","sinkron_terakhir":"22 Sep 2020 08:41:12","sekolah_id_enkrip":"0ED6932A0DEEEB4F0048                                                                                "}]