[{"nama":"SMK AL HADI GRESIK","sekolah_id":"96AA7B7A-C707-40D1-8E21-AB13985C0671","npsn":69899905,"jumlah_kirim":30,"ptk":9,"pegawai":1,"pd":65,"rombel":3,"jml_rk":3,"jml_lab":2,"jml_perpus":1,"induk_kecamatan":"Kec. Dukun","kode_wilayah_induk_kecamatan":"050114  ","induk_kabupaten":"Kab. Gresik","kode_wilayah_induk_kabupaten":"050100  ","induk_provinsi":"Prov. Jawa Timur","kode_wilayah_induk_provinsi":"050000  ","bentuk_pendidikan":"SMK","status_sekolah":"Swasta","sinkron_terakhir":"28 Sep 2020 08:50:39","sekolah_id_enkrip":"3B0D099DE0B6CEDAF914                                                                                "},{"nama":"SMK AL-KARIMI DUKUN","sekolah_id":"E55B3579-4964-4B63-8C91-CC1981292924","npsn":69967466,"jumlah_kirim":27,"ptk":5,"pegawai":1,"pd":16,"rombel":2,"jml_rk":3,"jml_lab":1,"jml_perpus":1,"induk_kecamatan":"Kec. Dukun","kode_wilayah_induk_kecamatan":"050114  ","induk_kabupaten":"Kab. Gresik","kode_wilayah_induk_kabupaten":"050100  ","induk_provinsi":"Prov. Jawa Timur","kode_wilayah_induk_provinsi":"050000  ","bentuk_pendidikan":"SMK","status_sekolah":"Swasta","sinkron_terakhir":"23 Sep 2020 09:51:34","sekolah_id_enkrip":"1077698EBFAEC2A6D482                                                                                "},{"nama":"SMK BUMI ASWAJA","sekolah_id":"07057F67-E8AD-4A65-9A17-A832BE248361","npsn":20576459,"jumlah_kirim":30,"ptk":4,"pegawai":3,"pd":65,"rombel":3,"jml_rk":3,"jml_lab":2,"jml_perpus":0,"induk_kecamatan":"Kec. Dukun","kode_wilayah_induk_kecamatan":"050114  ","induk_kabupaten":"Kab. Gresik","kode_wilayah_induk_kabupaten":"050100  ","induk_provinsi":"Prov. Jawa Timur","kode_wilayah_induk_provinsi":"050000  ","bentuk_pendidikan":"SMK","status_sekolah":"Swasta","sinkron_terakhir":"27 Sep 2020 09:30:07","sekolah_id_enkrip":"FD804FEED41C92E6037D                                                                                "},{"nama":"SMKS IHYAUL ULUM","sekolah_id":"ADA26237-5BDA-48E6-9B3D-C8F601F0C08B","npsn":20577783,"jumlah_kirim":43,"ptk":20,"pegawai":5,"pd":169,"rombel":9,"jml_rk":11,"jml_lab":5,"jml_perpus":1,"induk_kecamatan":"Kec. Dukun","kode_wilayah_induk_kecamatan":"050114  ","induk_kabupaten":"Kab. Gresik","kode_wilayah_induk_kabupaten":"050100  ","induk_provinsi":"Prov. Jawa Timur","kode_wilayah_induk_provinsi":"050000  ","bentuk_pendidikan":"SMK","status_sekolah":"Swasta","sinkron_terakhir":"24 Sep 2020 00:48:49","sekolah_id_enkrip":"1A5AA309E37B224DC67D                                                                                "},{"nama":"SMKS MASKUMAMBANG 1 DUKUN","sekolah_id":"C04EB916-7F27-4BF4-A129-3838B64C61AF","npsn":20500417,"jumlah_kirim":42,"ptk":21,"pegawai":3,"pd":303,"rombel":13,"jml_rk":15,"jml_lab":2,"jml_perpus":1,"induk_kecamatan":"Kec. Dukun","kode_wilayah_induk_kecamatan":"050114  ","induk_kabupaten":"Kab. Gresik","kode_wilayah_induk_kabupaten":"050100  ","induk_provinsi":"Prov. Jawa Timur","kode_wilayah_induk_provinsi":"050000  ","bentuk_pendidikan":"SMK","status_sekolah":"Swasta","sinkron_terakhir":"28 Sep 2020 10:38:43","sekolah_id_enkrip":"CAB4582D336BA25C9D65                                                                                "},{"nama":"SMKS MASKUMAMBANG 2 DUKUN","sekolah_id":"BC6C6B88-064D-4264-AD37-7AB22E83957C","npsn":20500416,"jumlah_kirim":30,"ptk":9,"pegawai":1,"pd":55,"rombel":5,"jml_rk":6,"jml_lab":1,"jml_perpus":1,"induk_kecamatan":"Kec. Dukun","kode_wilayah_induk_kecamatan":"050114  ","induk_kabupaten":"Kab. Gresik","kode_wilayah_induk_kabupaten":"050100  ","induk_provinsi":"Prov. Jawa Timur","kode_wilayah_induk_provinsi":"050000  ","bentuk_pendidikan":"SMK","status_sekolah":"Swasta","sinkron_terakhir":"16 Sep 2020 09:19:20","sekolah_id_enkrip":"1ACE0EB78584A10F4CC8                                                                                "},{"nama":"SMKS SUNAN DRAJAT","sekolah_id":"5D0FF963-F0B1-4576-B41F-E94FFEA58600","npsn":20555435,"jumlah_kirim":30,"ptk":8,"pegawai":3,"pd":124,"rombel":6,"jml_rk":6,"jml_lab":0,"jml_perpus":1,"induk_kecamatan":"Kec. Dukun","kode_wilayah_induk_kecamatan":"050114  ","induk_kabupaten":"Kab. Gresik","kode_wilayah_induk_kabupaten":"050100  ","induk_provinsi":"Prov. Jawa Timur","kode_wilayah_induk_provinsi":"050000  ","bentuk_pendidikan":"SMK","status_sekolah":"Swasta","sinkron_terakhir":"29 Sep 2020 18:20:17","sekolah_id_enkrip":"3414A8B3B7725D909E9D                                                                                "}]