[{"nama":"SMKN 1 DOKO","sekolah_id":"A471ACB3-4837-4217-9C36-56D9249552F6","npsn":20514364,"jumlah_kirim":106,"ptk":57,"pegawai":9,"pd":1760,"rombel":54,"jml_rk":33,"jml_lab":7,"jml_perpus":1,"induk_kecamatan":"Kec. Doko","kode_wilayah_induk_kecamatan":"051513  ","induk_kabupaten":"Kab. Blitar","kode_wilayah_induk_kabupaten":"051500  ","induk_provinsi":"Prov. Jawa Timur","kode_wilayah_induk_provinsi":"050000  ","bentuk_pendidikan":"SMK","status_sekolah":"Negeri","sinkron_terakhir":"02 Oct 2020 13:37:38","sekolah_id_enkrip":"943CAE8B422A0465230B                                                                                "}]