[{"nama":"SMKN 1 BERINGIN","sekolah_id":"1AEA91B8-0905-4DBE-837A-F49E4D93B426","npsn":10261468,"jumlah_kirim":69,"ptk":70,"pegawai":11,"pd":1360,"rombel":42,"jml_rk":30,"jml_lab":4,"jml_perpus":1,"induk_kecamatan":"Kec. Beringin","kode_wilayah_induk_kecamatan":"070129  ","induk_kabupaten":"Kab. Deli Serdang","kode_wilayah_induk_kabupaten":"070100  ","induk_provinsi":"Prov. Sumatera Utara","kode_wilayah_induk_provinsi":"070000  ","bentuk_pendidikan":"SMK","status_sekolah":"Negeri","sinkron_terakhir":"02 Oct 2020 16:22:15","sekolah_id_enkrip":"A619A187C823C3D721CD                                                                                "},{"nama":"SMK SWASTA JAYA KRAMA BERINGIN","sekolah_id":"3BF2123D-258B-4ED0-859E-7F584B1C4845","npsn":10214040,"jumlah_kirim":75,"ptk":29,"pegawai":4,"pd":554,"rombel":17,"jml_rk":20,"jml_lab":2,"jml_perpus":1,"induk_kecamatan":"Kec. Beringin","kode_wilayah_induk_kecamatan":"070129  ","induk_kabupaten":"Kab. Deli Serdang","kode_wilayah_induk_kabupaten":"070100  ","induk_provinsi":"Prov. Sumatera Utara","kode_wilayah_induk_provinsi":"070000  ","bentuk_pendidikan":"SMK","status_sekolah":"Swasta","sinkron_terakhir":"02 Oct 2020 13:36:32","sekolah_id_enkrip":"74B456CC3DA8CCBDAC5F                                                                                "},{"nama":"SMK SWASTA SINAR HARAPAN ","sekolah_id":"36D6564F-B916-4C0F-B9FE-E4357F246B3F","npsn":10214095,"jumlah_kirim":46,"ptk":20,"pegawai":3,"pd":458,"rombel":14,"jml_rk":17,"jml_lab":3,"jml_perpus":1,"induk_kecamatan":"Kec. Beringin","kode_wilayah_induk_kecamatan":"070129  ","induk_kabupaten":"Kab. Deli Serdang","kode_wilayah_induk_kabupaten":"070100  ","induk_provinsi":"Prov. Sumatera Utara","kode_wilayah_induk_provinsi":"070000  ","bentuk_pendidikan":"SMK","status_sekolah":"Swasta","sinkron_terakhir":"01 Oct 2020 13:25:57","sekolah_id_enkrip":"943D50485CDF503A01CC                                                                                "},{"nama":"SMKS AKP BERINGIN","sekolah_id":"C1D4D17B-BEE0-43C5-85E8-A6BD71A5A251","npsn":10219931,"jumlah_kirim":35,"ptk":14,"pegawai":3,"pd":204,"rombel":9,"jml_rk":9,"jml_lab":1,"jml_perpus":1,"induk_kecamatan":"Kec. Beringin","kode_wilayah_induk_kecamatan":"070129  ","induk_kabupaten":"Kab. Deli Serdang","kode_wilayah_induk_kabupaten":"070100  ","induk_provinsi":"Prov. Sumatera Utara","kode_wilayah_induk_provinsi":"070000  ","bentuk_pendidikan":"SMK","status_sekolah":"Swasta","sinkron_terakhir":"29 Sep 2020 10:50:06","sekolah_id_enkrip":"03FF0C75381AAE2480DF                                                                                "},{"nama":"SMKS DHARMA KARYA TI BERINGIN","sekolah_id":"7B7B974A-3EDC-4EF7-AFC7-308EE9AAFE48","npsn":10214079,"jumlah_kirim":21,"ptk":20,"pegawai":1,"pd":371,"rombel":14,"jml_rk":15,"jml_lab":1,"jml_perpus":1,"induk_kecamatan":"Kec. Beringin","kode_wilayah_induk_kecamatan":"070129  ","induk_kabupaten":"Kab. Deli Serdang","kode_wilayah_induk_kabupaten":"070100  ","induk_provinsi":"Prov. Sumatera Utara","kode_wilayah_induk_provinsi":"070000  ","bentuk_pendidikan":"SMK","status_sekolah":"Swasta","sinkron_terakhir":"26 Sep 2020 11:08:00","sekolah_id_enkrip":"D323FD2583797BB65DF4                                                                                "},{"nama":"SMKS LESTARI BERINGIN DELISERDANG","sekolah_id":"73EA7C9E-2EFA-4F3A-861C-77A1A727DE4B","npsn":10219932,"jumlah_kirim":33,"ptk":8,"pegawai":3,"pd":109,"rombel":4,"jml_rk":4,"jml_lab":1,"jml_perpus":5,"induk_kecamatan":"Kec. Beringin","kode_wilayah_induk_kecamatan":"070129  ","induk_kabupaten":"Kab. Deli Serdang","kode_wilayah_induk_kabupaten":"070100  ","induk_provinsi":"Prov. Sumatera Utara","kode_wilayah_induk_provinsi":"070000  ","bentuk_pendidikan":"SMK","status_sekolah":"Swasta","sinkron_terakhir":"15 Sep 2020 10:55:27","sekolah_id_enkrip":"71445F324413A4CB08FC                                                                                "},{"nama":"SMKS TKJ GEMILANG BANGSA","sekolah_id":"4EC32CA6-194C-47E5-B4F3-18247DBF43C8","npsn":10261663,"jumlah_kirim":35,"ptk":6,"pegawai":2,"pd":94,"rombel":4,"jml_rk":3,"jml_lab":1,"jml_perpus":1,"induk_kecamatan":"Kec. Beringin","kode_wilayah_induk_kecamatan":"070129  ","induk_kabupaten":"Kab. Deli Serdang","kode_wilayah_induk_kabupaten":"070100  ","induk_provinsi":"Prov. Sumatera Utara","kode_wilayah_induk_provinsi":"070000  ","bentuk_pendidikan":"SMK","status_sekolah":"Swasta","sinkron_terakhir":"25 Sep 2020 08:14:41","sekolah_id_enkrip":"C3677B014E3BE3C94C64                                                                                "}]