[{"nama":"SMK NEGERI 3 EMPAT LAWANG","sekolah_id":"243ACB22-DECA-43B0-831E-70DFC441E17F","npsn":69947883,"jumlah_kirim":12,"ptk":16,"pegawai":0,"pd":304,"rombel":10,"jml_rk":6,"jml_lab":0,"jml_perpus":0,"induk_kecamatan":"Kec. Pasemah Air Keruh","kode_wilayah_induk_kecamatan":"111107  ","induk_kabupaten":"Kab. Empat Lawang","kode_wilayah_induk_kabupaten":"111100  ","induk_provinsi":"Prov. Sumatera Selatan","kode_wilayah_induk_provinsi":"110000  ","bentuk_pendidikan":"SMK","status_sekolah":"Negeri","sinkron_terakhir":"02 Oct 2020 19:03:21","sekolah_id_enkrip":"DB7478DB789EC48EDA8C                                                                                "}]