[{"nama":"SMK BINA CIPTA PALEMBANG","sekolah_id":"9C9F578A-9CCA-4C0A-96D0-6EB8F00BCAF9","npsn":10603704,"jumlah_kirim":60,"ptk":23,"pegawai":2,"pd":321,"rombel":15,"jml_rk":15,"jml_lab":3,"jml_perpus":1,"induk_kecamatan":"Kec. Kalidoni","kode_wilayah_induk_kecamatan":"116014  ","induk_kabupaten":"Kota Palembang","kode_wilayah_induk_kabupaten":"116000  ","induk_provinsi":"Prov. Sumatera Selatan","kode_wilayah_induk_provinsi":"110000  ","bentuk_pendidikan":"SMK","status_sekolah":"Swasta","sinkron_terakhir":"21 Sep 2020 14:45:56","sekolah_id_enkrip":"BE2E2C9DABC75E59F848                                                                                "},{"nama":"SMK FARMASI BINA MEDIKA PALEMBANG","sekolah_id":"4E598FFD-9B25-4865-A8EF-30F14E1168B4","npsn":69756887,"jumlah_kirim":24,"ptk":6,"pegawai":2,"pd":131,"rombel":4,"jml_rk":5,"jml_lab":3,"jml_perpus":1,"induk_kecamatan":"Kec. Kalidoni","kode_wilayah_induk_kecamatan":"116014  ","induk_kabupaten":"Kota Palembang","kode_wilayah_induk_kabupaten":"116000  ","induk_provinsi":"Prov. Sumatera Selatan","kode_wilayah_induk_provinsi":"110000  ","bentuk_pendidikan":"SMK","status_sekolah":"Swasta","sinkron_terakhir":"29 Sep 2020 10:34:37","sekolah_id_enkrip":"E7ED44416C2BE75EDDA9                                                                                "},{"nama":"SMK PGRI 02 PALEMBANG","sekolah_id":"59DA9814-F6C5-4C39-8904-85F0EDE1434D","npsn":10603701,"jumlah_kirim":49,"ptk":52,"pegawai":6,"pd":1380,"rombel":44,"jml_rk":24,"jml_lab":5,"jml_perpus":1,"induk_kecamatan":"Kec. Kalidoni","kode_wilayah_induk_kecamatan":"116014  ","induk_kabupaten":"Kota Palembang","kode_wilayah_induk_kabupaten":"116000  ","induk_provinsi":"Prov. Sumatera Selatan","kode_wilayah_induk_provinsi":"110000  ","bentuk_pendidikan":"SMK","status_sekolah":"Swasta","sinkron_terakhir":"01 Oct 2020 10:21:12","sekolah_id_enkrip":"AD332AB5DD14C9909E7A                                                                                "},{"nama":"SMK PGRI 03 PALEMBANG","sekolah_id":"27924530-9091-4C04-96D0-6C3DD1C12E7E","npsn":69755982,"jumlah_kirim":37,"ptk":4,"pegawai":1,"pd":238,"rombel":8,"jml_rk":10,"jml_lab":1,"jml_perpus":1,"induk_kecamatan":"Kec. Kalidoni","kode_wilayah_induk_kecamatan":"116014  ","induk_kabupaten":"Kota Palembang","kode_wilayah_induk_kabupaten":"116000  ","induk_provinsi":"Prov. Sumatera Selatan","kode_wilayah_induk_provinsi":"110000  ","bentuk_pendidikan":"SMK","status_sekolah":"Swasta","sinkron_terakhir":"02 Oct 2020 20:35:16","sekolah_id_enkrip":"2FC1D363909917D7BC8B                                                                                "},{"nama":"SMK TAQWA PALEMBANG","sekolah_id":"CF4CF848-71A4-451B-9507-85FC635D72C0","npsn":10603682,"jumlah_kirim":33,"ptk":4,"pegawai":2,"pd":74,"rombel":4,"jml_rk":4,"jml_lab":0,"jml_perpus":1,"induk_kecamatan":"Kec. Kalidoni","kode_wilayah_induk_kecamatan":"116014  ","induk_kabupaten":"Kota Palembang","kode_wilayah_induk_kabupaten":"116000  ","induk_provinsi":"Prov. Sumatera Selatan","kode_wilayah_induk_provinsi":"110000  ","bentuk_pendidikan":"SMK","status_sekolah":"Swasta","sinkron_terakhir":"02 Oct 2020 16:06:48","sekolah_id_enkrip":"F2AFAC56AB286D11F2BB                                                                                "}]