[{"nama":"SMKN 1 KALIORANG","sekolah_id":"52B7D6CC-4662-44D7-A871-1C304FD88EED","npsn":30407725,"jumlah_kirim":24,"ptk":22,"pegawai":7,"pd":403,"rombel":15,"jml_rk":10,"jml_lab":2,"jml_perpus":1,"induk_kecamatan":"Kec. Kaliorang","kode_wilayah_induk_kecamatan":"161006  ","induk_kabupaten":"Kab. Kutai Timur","kode_wilayah_induk_kabupaten":"161000  ","induk_provinsi":"Prov. Kalimantan Timur","kode_wilayah_induk_provinsi":"160000  ","bentuk_pendidikan":"SMK","status_sekolah":"Negeri","sinkron_terakhir":"28 Sep 2020 21:44:06","sekolah_id_enkrip":"77290380F9B01AD24F49                                                                                "}]