[{"nama":"SMK NEGERI 1 MODOINDING","sekolah_id":"F158D376-5A15-4167-A63C-B50E7D956739","npsn":40103901,"jumlah_kirim":23,"ptk":23,"pegawai":1,"pd":346,"rombel":13,"jml_rk":13,"jml_lab":1,"jml_perpus":1,"induk_kecamatan":"Kec. Modoinding","kode_wilayah_induk_kecamatan":"170501  ","induk_kabupaten":"Kab. Minahasa Selatan","kode_wilayah_induk_kabupaten":"170500  ","induk_provinsi":"Prov. Sulawesi Utara","kode_wilayah_induk_provinsi":"170000  ","bentuk_pendidikan":"SMK","status_sekolah":"Negeri","sinkron_terakhir":"02 Oct 2020 09:08:07","sekolah_id_enkrip":"92E8BC19BE7E03182FEE                                                                                "}]