[{"nama":"SMKS PIONEER MANADO","sekolah_id":"EDFD3F62-5E73-4C17-A79C-A246A10FEA4D","npsn":40104575,"jumlah_kirim":12,"ptk":9,"pegawai":2,"pd":27,"rombel":9,"jml_rk":9,"jml_lab":1,"jml_perpus":1,"induk_kecamatan":"Kec. Paal Dua","kode_wilayah_induk_kecamatan":"176010  ","induk_kabupaten":"Kota Manado","kode_wilayah_induk_kabupaten":"176000  ","induk_provinsi":"Prov. Sulawesi Utara","kode_wilayah_induk_provinsi":"170000  ","bentuk_pendidikan":"SMK","status_sekolah":"Swasta","sinkron_terakhir":"03 Sep 2020 21:25:48","sekolah_id_enkrip":"6A569421F4808DDD98CC                                                                                "}]