[{"nama":"SMKN 1 DONDO","sekolah_id":"2F8AB832-F62E-4CB8-8E2A-C10F9F847689","npsn":60728507,"jumlah_kirim":36,"ptk":15,"pegawai":4,"pd":217,"rombel":6,"jml_rk":3,"jml_lab":1,"jml_perpus":1,"induk_kecamatan":"Kec. Dondo","kode_wilayah_induk_kecamatan":"180603  ","induk_kabupaten":"Kab. Tolitoli","kode_wilayah_induk_kabupaten":"180600  ","induk_provinsi":"Prov. Sulawesi Tengah","kode_wilayah_induk_provinsi":"180000  ","bentuk_pendidikan":"SMK","status_sekolah":"Negeri","sinkron_terakhir":"21 Sep 2020 22:27:44","sekolah_id_enkrip":"6BCFB5A18FC7F2E8A5A5                                                                                "}]