[{"nama":"SMKN 9 WAJO","sekolah_id":"43B99BAC-5BBA-4D6B-AA09-07FFDADD5CAC","npsn":69956699,"jumlah_kirim":50,"ptk":9,"pegawai":4,"pd":198,"rombel":9,"jml_rk":7,"jml_lab":1,"jml_perpus":0,"induk_kecamatan":"Kec. Belawa","kode_wilayah_induk_kecamatan":"190809  ","induk_kabupaten":"Kab. Wajo","kode_wilayah_induk_kabupaten":"190800  ","induk_provinsi":"Prov. Sulawesi Selatan","kode_wilayah_induk_provinsi":"190000  ","bentuk_pendidikan":"SMK","status_sekolah":"Negeri","sinkron_terakhir":"30 Sep 2020 18:48:15","sekolah_id_enkrip":"6EFC385C523C27726EF1                                                                                "}]