[{"nama":"SMKN 5 KONAWE SELATAN","sekolah_id":"795E3577-D444-419E-8AA8-6BB5C5140A7E","npsn":40404851,"jumlah_kirim":46,"ptk":10,"pegawai":2,"pd":317,"rombel":10,"jml_rk":10,"jml_lab":7,"jml_perpus":1,"induk_kecamatan":"Kec. Lainea","kode_wilayah_induk_kecamatan":"200504  ","induk_kabupaten":"Kab. Konawe Selatan","kode_wilayah_induk_kabupaten":"200500  ","induk_provinsi":"Prov. Sulawesi Tenggara","kode_wilayah_induk_provinsi":"200000  ","bentuk_pendidikan":"SMK","status_sekolah":"Negeri","sinkron_terakhir":"16 Sep 2020 00:53:41","sekolah_id_enkrip":"AEF3AD6CD88AC72C511A                                                                                "}]