[{"nama":"SMKN 1 BOVEN DIGOEL","sekolah_id":"1840B2B6-2A4C-4B2F-A188-0B90C096BE7F","npsn":60305245,"jumlah_kirim":56,"ptk":53,"pegawai":2,"pd":508,"rombel":17,"jml_rk":22,"jml_lab":3,"jml_perpus":1,"induk_kecamatan":"Kec. Mandobo","kode_wilayah_induk_kecamatan":"251303  ","induk_kabupaten":"Kab. Boven Digoel","kode_wilayah_induk_kabupaten":"251300  ","induk_provinsi":"Prov. Papua","kode_wilayah_induk_provinsi":"250000  ","bentuk_pendidikan":"SMK","status_sekolah":"Negeri","sinkron_terakhir":"02 Oct 2020 07:23:18","sekolah_id_enkrip":"31202BFFF71389401FFC                                                                                "}]