[{"nama":"SMKN PERTANIAN WAROPEN","sekolah_id":"9D27436C-8094-4FD7-8258-5C587C08BCCC","npsn":60304980,"jumlah_kirim":4,"ptk":12,"pegawai":3,"pd":58,"rombel":5,"jml_rk":7,"jml_lab":1,"jml_perpus":1,"induk_kecamatan":"Kec. Masirei","kode_wilayah_induk_kecamatan":"252602  ","induk_kabupaten":"Kab. Waropen","kode_wilayah_induk_kabupaten":"252600  ","induk_provinsi":"Prov. Papua","kode_wilayah_induk_provinsi":"250000  ","bentuk_pendidikan":"SMK","status_sekolah":"Negeri","sinkron_terakhir":"17 Sep 2020 23:28:33","sekolah_id_enkrip":"BC4279BCCD7ED0245991                                                                                "}]