[{"nama":"SMKN 1 BONEPANTAI","sekolah_id":"CE5034FE-B525-4187-B1EC-3185AD572F30","npsn":40500895,"jumlah_kirim":25,"ptk":21,"pegawai":3,"pd":192,"rombel":11,"jml_rk":11,"jml_lab":3,"jml_perpus":1,"induk_kecamatan":"Kec. Bonepantai","kode_wilayah_induk_kecamatan":"300404  ","induk_kabupaten":"Kab. Bone Bolango","kode_wilayah_induk_kabupaten":"300400  ","induk_provinsi":"Prov. Gorontalo","kode_wilayah_induk_provinsi":"300000  ","bentuk_pendidikan":"SMK","status_sekolah":"Negeri","sinkron_terakhir":"30 Sep 2020 22:05:26","sekolah_id_enkrip":"9E4CA35B59E17DF725BF                                                                                "}]