[{"nama":"SMK BISNIS DAN MANAJEMEN KEBAR","sekolah_id":"280E8632-3F31-446D-8AF3-EB543F9DADE3","npsn":69899945,"jumlah_kirim":10,"ptk":10,"pegawai":3,"pd":54,"rombel":3,"jml_rk":3,"jml_lab":0,"jml_perpus":0,"induk_kecamatan":"Kec. Kebar","kode_wilayah_induk_kecamatan":"320908  ","induk_kabupaten":"Kab. Tambrauw","kode_wilayah_induk_kabupaten":"320900  ","induk_provinsi":"Prov. Papua Barat","kode_wilayah_induk_provinsi":"320000  ","bentuk_pendidikan":"SMK","status_sekolah":"Negeri","sinkron_terakhir":"29 Aug 2020 17:25:49","sekolah_id_enkrip":"5AB49A3CDAEC51CE8480                                                                                "}]