[{"nama":"SMKN 2 SORONG","sekolah_id":"94158EB0-C8BD-493D-B49A-733DBA8131A4","npsn":60403609,"jumlah_kirim":12,"ptk":34,"pegawai":4,"pd":355,"rombel":17,"jml_rk":18,"jml_lab":3,"jml_perpus":1,"induk_kecamatan":"Kec. Sorong Kota","kode_wilayah_induk_kecamatan":"326003  ","induk_kabupaten":"Kota Sorong","kode_wilayah_induk_kabupaten":"326000  ","induk_provinsi":"Prov. Papua Barat","kode_wilayah_induk_provinsi":"320000  ","bentuk_pendidikan":"SMK","status_sekolah":"Negeri","sinkron_terakhir":"26 Sep 2020 11:23:54","sekolah_id_enkrip":"72FE37C02E06F85EA830                                                                                "},{"nama":"SUPM NEGERI SORONG","sekolah_id":"A41711D8-A319-4CFB-A1E1-FF2B694FBC40","npsn":60404134,"jumlah_kirim":23,"ptk":24,"pegawai":1,"pd":444,"rombel":12,"jml_rk":12,"jml_lab":4,"jml_perpus":1,"induk_kecamatan":"Kec. Sorong Kota","kode_wilayah_induk_kecamatan":"326003  ","induk_kabupaten":"Kota Sorong","kode_wilayah_induk_kabupaten":"326000  ","induk_provinsi":"Prov. Papua Barat","kode_wilayah_induk_provinsi":"320000  ","bentuk_pendidikan":"SMK","status_sekolah":"Negeri","sinkron_terakhir":"14 Sep 2020 13:26:31","sekolah_id_enkrip":"440833442FC5C12CCEC7                                                                                "},{"nama":"SMKS YPK IMANUEL SORONG","sekolah_id":"1B495CD0-5718-4386-9714-B6DF511F44F8","npsn":60400388,"jumlah_kirim":26,"ptk":16,"pegawai":3,"pd":321,"rombel":12,"jml_rk":16,"jml_lab":3,"jml_perpus":1,"induk_kecamatan":"Kec. Sorong Kota","kode_wilayah_induk_kecamatan":"326003  ","induk_kabupaten":"Kota Sorong","kode_wilayah_induk_kabupaten":"326000  ","induk_provinsi":"Prov. Papua Barat","kode_wilayah_induk_provinsi":"320000  ","bentuk_pendidikan":"SMK","status_sekolah":"Swasta","sinkron_terakhir":"29 Sep 2020 10:28:24","sekolah_id_enkrip":"BF901157811F772B7D78                                                                                "}]